re.py
setup.py
micropython_re_pcre.egg-info/PKG-INFO
micropython_re_pcre.egg-info/SOURCES.txt
micropython_re_pcre.egg-info/dependency_links.txt
micropython_re_pcre.egg-info/requires.txt
micropython_re_pcre.egg-info/top_level.txt