Metadata-Version: 1.0
Name: micropython-re-pcre
Version: 0.2.1
Summary: re-pcre module for MicroPython
Home-page: https://github.com/micropython/micropython/issues/405
Author: MicroPython Developers
Author-email: micro-python@googlegroups.com
License: MIT
Platform: UNKNOWN
